MANIFEST.in
README.txt
setup.cfg
setup.py
docs/HISTORY.txt
docs/INSTALL.txt
docs/LICENSE.GPL
docs/LICENSE.txt
redomino/__init__.py
redomino/__init__.pyc
redomino.redirectparent.egg-info/PKG-INFO
redomino.redirectparent.egg-info/SOURCES.txt
redomino.redirectparent.egg-info/dependency_links.txt
redomino.redirectparent.egg-info/entry_points.txt
redomino.redirectparent.egg-info/namespace_packages.txt
redomino.redirectparent.egg-info/not-zip-safe
redomino.redirectparent.egg-info/requires.txt
redomino.redirectparent.egg-info/top_level.txt
redomino/redirectparent/__init__.py
redomino/redirectparent/configure.zcml
redomino/redirectparent/handlers.py
redomino/redirectparent/interface.py
redomino/redirectparent/tests.py
redomino/redirectparent/browser/__init__.py
redomino/redirectparent/browser/applyinterface.py
redomino/redirectparent/browser/configure.zcml
redomino/redirectparent/browser/viewlets.py
redomino/redirectparent/browser/resources/jquery.contextlink.js
redomino/redirectparent/browser/resources/plone.contextlink.css
redomino/redirectparent/browser/resources/plone.contextlink.js
redomino/redirectparent/browser/resources/tests/jquery-1.4.4.min.js
redomino/redirectparent/browser/resources/tests/qunit.css
redomino/redirectparent/browser/resources/tests/qunit.js
redomino/redirectparent/browser/resources/tests/test.html
redomino/redirectparent/browser/resources/tests/test.js
redomino/redirectparent/profiles/default/cssregistry.xml
redomino/redirectparent/profiles/default/jsregistry.xml
redomino/redirectparent/profiles/default/metadata.xml
redomino/redirectparent/profiles/default/propertiestool.xml
redomino/redirectparent/profiles/default/tinymce.xml
redomino/redirectparent/profiles/default/types.xml
redomino/redirectparent/profiles/default/workflows.xml
redomino/redirectparent/profiles/default/types/NonIndexedFolder.xml